decent/__init__.py
decent/channel.py
decent/emote.py
decent/errors.py
decent/message.py
decent/server.py
decent/user.py
decent.py-1.0.0b2.dist-info/DESCRIPTION.rst
decent.py-1.0.0b2.dist-info/METADATA
decent.py-1.0.0b2.dist-info/RECORD
decent.py-1.0.0b2.dist-info/WHEEL
decent.py-1.0.0b2.dist-info/metadata.json
decent.py-1.0.0b2.dist-info/top_level.txt
