Metadata-Version: 2.0
Name: decent.py
Version: 1.0.0b2
Summary: Python API wrapper for Decent
Home-page: https://github.com/TheInitializer/decent.py
Author: xn--cr8h
Author-email: theinitializer.py@gmail.com
License: UNKNOWN
Requires-Dist: requests
Requires-Dist: websocket-client
Provides-Extra: test
Requires-Dist: typing; extra == 'test'
